pictil/__init__.py
pictil/main.py
pictil-1.0.1.dist-info/DESCRIPTION.rst
pictil-1.0.1.dist-info/METADATA
pictil-1.0.1.dist-info/RECORD
pictil-1.0.1.dist-info/WHEEL
pictil-1.0.1.dist-info/entry_points.txt
pictil-1.0.1.dist-info/metadata.json
pictil-1.0.1.dist-info/top_level.txt
