Metadata-Version: 2.0
Name: pictil
Version: 1.0.1
Summary: Provies renaming utility for Nikon output files.
Home-page: https://github.com/ChrisoftheBoyerClan/pictil.py
Author: Christopher Boyer
Author-email: ChrisoftheBoyerClan@gmail.com
License: MIT
Keywords: rename nikon pictures
Platform: UNKNOWN
